{
  "data": [
    {
      "id": 1,
      "attributes": {
        "NameWitness": "Guillaume",
        "DateExperience": "2022-07-07",
        "createdAt": "2022-12-16T13:49:42.322Z",
        "updatedAt": "2022-12-16T15:38:45.747Z",
        "publishedAt": "2022-12-16T13:49:43.965Z",
        "NoteSecurity": 4,
        "NoteBalisage": 3,
        "NoteInterest": 4,
        "NoteService": 4,
        "Titre": "Un cadre très agréable ",
        "Description": "J'ai découvert Eurovelo cet été et me suis lancée sur le parcours Lille > Wattrelos pour essayer, étant du secteur, et je dois dire que c'était une très bonne expérience, j'y ai découvert des coins sympas que je ne connaissais pas!",
        "DatePublish": "2022-10-25T09:32:00.000Z",
        "Picture": {
          "data": [
            {
              "id": 28,
              "attributes": {
                "name": "25368625267_7886eeca71_k.jpg",
                "alternativeText": null,
                "caption": null,
                "width": 2048,
                "height": 1365,
                "formats": {
                  "thumbnail": {
                    "name": "thumbnail_25368625267_7886eeca71_k.jpg",
                    "hash": "thumbnail_25368625267_7886eeca71_k_74cc49e575",
                    "ext": ".jpg",
                    "mime": "image/jpeg",
                    "path": null,
                    "width": 234,
                    "height": 156,
                    "size": 9.88,
                    "url": "/uploads/thumbnail_25368625267_7886eeca71_k_74cc49e575.jpg"
                  },
                  "small": {
                    "name": "small_25368625267_7886eeca71_k.jpg",
                    "hash": "small_25368625267_7886eeca71_k_74cc49e575",
                    "ext": ".jpg",
                    "mime": "image/jpeg",
                    "path": null,
                    "width": 500,
                    "height": 333,
                    "size": 40.1,
                    "url": "/uploads/small_25368625267_7886eeca71_k_74cc49e575.jpg"
                  },
                  "medium": {
                    "name": "medium_25368625267_7886eeca71_k.jpg",
                    "hash": "medium_25368625267_7886eeca71_k_74cc49e575",
                    "ext": ".jpg",
                    "mime": "image/jpeg",
                    "path": null,
                    "width": 750,
                    "height": 500,
                    "size": 89.97,
                    "url": "/uploads/medium_25368625267_7886eeca71_k_74cc49e575.jpg"
                  },
                  "large": {
                    "name": "large_25368625267_7886eeca71_k.jpg",
                    "hash": "large_25368625267_7886eeca71_k_74cc49e575",
                    "ext": ".jpg",
                    "mime": "image/jpeg",
                    "path": null,
                    "width": 1000,
                    "height": 667,
                    "size": 161.32,
                    "url": "/uploads/large_25368625267_7886eeca71_k_74cc49e575.jpg"
                  }
                },
                "hash": "25368625267_7886eeca71_k_74cc49e575",
                "ext": ".jpg",
                "mime": "image/jpeg",
                "size": 717.39,
                "url": "/uploads/25368625267_7886eeca71_k_74cc49e575.jpg",
                "previewUrl": null,
                "provider": "local",
                "provider_metadata": null,
                "createdAt": "2022-12-16T13:49:35.065Z",
                "updatedAt": "2022-12-16T13:49:35.065Z"
              }
            }
          ]
        },
        "description_maps": {
          "data": [
            {
              "id": 4,
              "attributes": {
                "type": "Nature et patrimoine",
                "description": "Vous pédalerez sur une ancienne voie ferrée devenue voie verte, très boisée où vous croiserez probablement quelques roulottes et cavaliers [...]",
                "createdAt": "2022-12-15T12:41:48.493Z",
                "updatedAt": "2022-12-19T08:46:27.465Z",
                "publishedAt": "2022-12-15T12:41:49.640Z",
                "habitude_nb": 1,
                "id_infos": 6,
                "long_desc": "Après Lille, vous pédalerez sur une ancienne voie ferrée devenue voie verte, très boisée où vous croiserez probablement quelques roulottes et cavaliers. Puis les forêts laissent la place aux landes. Balade à vélo très nature en immersion totale, vous déroulez la voie verte en toute sérénité. A quelques kilomètres de l'eurovelo, son lac et sa forêt dont la célèbre roche tremblante valent largement la peine d’affronter une montée prononcée. Vous terminerez cette étape à Carhaix, le lieu de rendez-vous des \"Vieilles charrues\"!",
                "depart": "Lille",
                "arrive": "Wattrelos"
              }
            }
          ]
        }
      }
    },
    {
      "id": 2,
      "attributes": {
        "NameWitness": "Antoine M ",
        "DateExperience": "2022-10-26",
        "createdAt": "2022-12-16T13:52:35.846Z",
        "updatedAt": "2022-12-16T15:39:47.392Z",
        "publishedAt": "2022-12-16T13:52:39.207Z",
        "NoteSecurity": 3,
        "NoteBalisage": 2,
        "NoteInterest": 4,
        "NoteService": 3,
        "Titre": "Sympa ",
        "Description": "J'adore le vélo et je fais toujours les mêmes parcours car je ne sais pas où aller, grâce à Eurovelo j'en ai découvert d'autres, celui ci était sympa mais pas le meilleur",
        "DatePublish": "2022-11-15T14:59:00.000Z",
        "Picture": {
          "data": [
            {
              "id": 10,
              "attributes": {
                "name": "bridge.jpg",
                "alternativeText": null,
                "caption": null,
                "width": 2048,
                "height": 1365,
                "formats": {
                  "thumbnail": {
                    "name": "thumbnail_bridge.jpg",
                    "hash": "thumbnail_bridge_a65c304112",
                    "ext": ".jpg",
                    "mime": "image/jpeg",
                    "path": null,
                    "width": 234,
                    "height": 156,
                    "size": 11.92,
                    "url": "/uploads/thumbnail_bridge_a65c304112.jpg"
                  },
                  "small": {
                    "name": "small_bridge.jpg",
                    "hash": "small_bridge_a65c304112",
                    "ext": ".jpg",
                    "mime": "image/jpeg",
                    "path": null,
                    "width": 500,
                    "height": 333,
                    "size": 45.42,
                    "url": "/uploads/small_bridge_a65c304112.jpg"
                  },
                  "medium": {
                    "name": "medium_bridge.jpg",
                    "hash": "medium_bridge_a65c304112",
                    "ext": ".jpg",
                    "mime": "image/jpeg",
                    "path": null,
                    "width": 750,
                    "height": 500,
                    "size": 95.79,
                    "url": "/uploads/medium_bridge_a65c304112.jpg"
                  },
                  "large": {
                    "name": "large_bridge.jpg",
                    "hash": "large_bridge_a65c304112",
                    "ext": ".jpg",
                    "mime": "image/jpeg",
                    "path": null,
                    "width": 1000,
                    "height": 667,
                    "size": 162.92,
                    "url": "/uploads/large_bridge_a65c304112.jpg"
                  }
                },
                "hash": "bridge_a65c304112",
                "ext": ".jpg",
                "mime": "image/jpeg",
                "size": 626.39,
                "url": "/uploads/bridge_a65c304112.jpg",
                "previewUrl": null,
                "provider": "local",
                "provider_metadata": null,
                "createdAt": "2022-12-15T10:19:32.780Z",
                "updatedAt": "2022-12-15T10:19:32.780Z"
              }
            }
          ]
        },
        "description_maps": {
          "data": [
            {
              "id": 3,
              "attributes": {
                "type": "Nature, Patrimoine, Site Incontournable",
                "description": "Laissez-vous surprendre par les paysages de Saint Omer, ses pins et son piton rocheux lui donne un petit air de Méditerranée [...]",
                "createdAt": "2022-12-15T12:39:05.447Z",
                "updatedAt": "2022-12-19T08:45:40.950Z",
                "publishedAt": "2022-12-15T12:39:06.274Z",
                "habitude_nb": 3,
                "id_infos": 4,
                "long_desc": "Laissez-vous surprendre par les paysages de Saint Omer, ses pins et son piton rocheux lui donne un petit air de Méditerranée, qui fait tout le charme de cette section de la véloroute L'EuroVelo. Puis l'on découvre Aire sur la Lys, à la croisée de 7 vallées vallonnées, de la Vilaine et de l’Oust ! Soyez vigilant au niveau du barrage de la Potinais et lors de la traversée de Redon.",
                "depart": "Saint Omer ",
                "arrive": "Aire sur la Lys"
              }
            }
          ]
        }
      }
    },
    {
      "id": 3,
      "attributes": {
        "NameWitness": "Julie",
        "DateExperience": "2022-09-02",
        "createdAt": "2022-12-16T13:54:55.095Z",
        "updatedAt": "2022-12-16T15:40:15.483Z",
        "publishedAt": "2022-12-16T13:54:58.775Z",
        "NoteSecurity": 5,
        "NoteBalisage": 3,
        "NoteInterest": 4,
        "NoteService": 4,
        "Titre": "Un parcours agréable en famille",
        "Description": "Nous cherchions un parcours faisable en famille, quelle joie d'avoir pu le découvrir sous un grand soleil de fin d'été!",
        "DatePublish": "2022-09-04T16:32:00.000Z",
        "Picture": {
          "data": [
            {
              "id": 30,
              "attributes": {
                "name": "coupletemoignage.jpg",
                "alternativeText": null,
                "caption": null,
                "width": 1024,
                "height": 683,
                "formats": {
                  "thumbnail": {
                    "name": "thumbnail_coupletemoignage.jpg",
                    "hash": "thumbnail_coupletemoignage_14952d66bf",
                    "ext": ".jpg",
                    "mime": "image/jpeg",
                    "path": null,
                    "width": 234,
                    "height": 156,
                    "size": 11.69,
                    "url": "/uploads/thumbnail_coupletemoignage_14952d66bf.jpg"
                  },
                  "small": {
                    "name": "small_coupletemoignage.jpg",
                    "hash": "small_coupletemoignage_14952d66bf",
                    "ext": ".jpg",
                    "mime": "image/jpeg",
                    "path": null,
                    "width": 500,
                    "height": 333,
                    "size": 44.02,
                    "url": "/uploads/small_coupletemoignage_14952d66bf.jpg"
                  },
                  "medium": {
                    "name": "medium_coupletemoignage.jpg",
                    "hash": "medium_coupletemoignage_14952d66bf",
                    "ext": ".jpg",
                    "mime": "image/jpeg",
                    "path": null,
                    "width": 750,
                    "height": 500,
                    "size": 92.55,
                    "url": "/uploads/medium_coupletemoignage_14952d66bf.jpg"
                  },
                  "large": {
                    "name": "large_coupletemoignage.jpg",
                    "hash": "large_coupletemoignage_14952d66bf",
                    "ext": ".jpg",
                    "mime": "image/jpeg",
                    "path": null,
                    "width": 1000,
                    "height": 667,
                    "size": 152.46,
                    "url": "/uploads/large_coupletemoignage_14952d66bf.jpg"
                  }
                },
                "hash": "coupletemoignage_14952d66bf",
                "ext": ".jpg",
                "mime": "image/jpeg",
                "size": 166.09,
                "url": "/uploads/coupletemoignage_14952d66bf.jpg",
                "previewUrl": null,
                "provider": "local",
                "provider_metadata": null,
                "createdAt": "2022-12-16T13:53:27.370Z",
                "updatedAt": "2022-12-16T13:53:27.370Z"
              }
            }
          ]
        },
        "description_maps": {
          "data": [
            {
              "id": 1,
              "attributes": {
                "type": "Nature, Patrimoine, Site Incontournable",
                "description": "Après une pause rafraîchissante au petit port , L'EuroVelo continue à travers la forêt domaniale de Sainte-Eulalie avant d’embrasser l’océan [...]",
                "createdAt": "2022-12-14T12:56:02.878Z",
                "updatedAt": "2022-12-19T08:45:57.102Z",
                "publishedAt": "2022-12-15T08:02:06.541Z",
                "habitude_nb": 3,
                "id_infos": 2,
                "long_desc": "Après une pause rafraîchissante au petit port , L'EuroVelo continue à travers la forêt domaniale de Sainte-Eulalie avant d’embrasser à nouveau l’océan.\nCe dernier vous dévoilera son plus beau visage dès votre arrivée sur la station familiale de Mimizan-Plage, aussi appelée la Perle de la Côte d’Argent.",
                "depart": "Watten",
                "arrive": "St Omer"
              }
            }
          ]
        }
      }
    },
    {
      "id": 4,
      "attributes": {
        "NameWitness": "Ayoub",
        "DateExperience": "2022-11-28",
        "createdAt": "2022-12-16T13:58:18.378Z",
        "updatedAt": "2022-12-20T13:13:22.000Z",
        "publishedAt": "2022-12-16T13:58:20.395Z",
        "NoteSecurity": 5,
        "NoteBalisage": 4,
        "NoteInterest": 3,
        "NoteService": 3,
        "Titre": "Un excellent moment en famille",
        "Description": "Même par ce froid, nous avons adoré ce moment avec mon épouse et notre fils. Parcours très sécurisé et agréable.",
        "DatePublish": "2022-11-30T23:03:00.000Z",
        "Picture": {
          "data": [
            {
              "id": 6,
              "attributes": {
                "name": "sundown.jpg",
                "alternativeText": null,
                "caption": null,
                "width": 2048,
                "height": 1537,
                "formats": {
                  "thumbnail": {
                    "name": "thumbnail_sundown.jpg",
                    "hash": "thumbnail_sundown_bf490bd831",
                    "ext": ".jpg",
                    "mime": "image/jpeg",
                    "path": null,
                    "width": 208,
                    "height": 156,
                    "size": 3.76,
                    "url": "/uploads/thumbnail_sundown_bf490bd831.jpg"
                  },
                  "medium": {
                    "name": "medium_sundown.jpg",
                    "hash": "medium_sundown_bf490bd831",
                    "ext": ".jpg",
                    "mime": "image/jpeg",
                    "path": null,
                    "width": 750,
                    "height": 563,
                    "size": 33.17,
                    "url": "/uploads/medium_sundown_bf490bd831.jpg"
                  },
                  "large": {
                    "name": "large_sundown.jpg",
                    "hash": "large_sundown_bf490bd831",
                    "ext": ".jpg",
                    "mime": "image/jpeg",
                    "path": null,
                    "width": 1000,
                    "height": 750,
                    "size": 57.22,
                    "url": "/uploads/large_sundown_bf490bd831.jpg"
                  },
                  "small": {
                    "name": "small_sundown.jpg",
                    "hash": "small_sundown_bf490bd831",
                    "ext": ".jpg",
                    "mime": "image/jpeg",
                    "path": null,
                    "width": 500,
                    "height": 375,
                    "size": 16.14,
                    "url": "/uploads/small_sundown_bf490bd831.jpg"
                  }
                },
                "hash": "sundown_bf490bd831",
                "ext": ".jpg",
                "mime": "image/jpeg",
                "size": 276.07,
                "url": "/uploads/sundown_bf490bd831.jpg",
                "previewUrl": null,
                "provider": "local",
                "provider_metadata": null,
                "createdAt": "2022-12-14T10:53:42.036Z",
                "updatedAt": "2022-12-19T08:09:40.252Z"
              }
            }
          ]
        },
        "description_maps": {
          "data": [
            {
              "id": 2,
              "attributes": {
                "type": "Nature et patrimoine",
                "description": "Saint Venant est une étape incontournable de L'EuroVelo ! Station balnéaire réputée, elle est dotée d'un port actif axé sur la pêche [...]",
                "createdAt": "2022-12-15T10:20:33.187Z",
                "updatedAt": "2022-12-19T08:45:50.169Z",
                "publishedAt": "2022-12-15T10:23:53.141Z",
                "habitude_nb": 2,
                "id_infos": 3,
                "long_desc": "Saint Venant est une étape incontournable de L'EuroVelo ! Station balnéaire réputée, elle est dotée d'un port actif axé sur la pêche des poissons bleus : sardines et maquereaux. Prenez le temps de flâner sur sa grande plage avant de reprendre la route en direction de la côte vers Bethune.\n\nLa véloroute L'EuroVelo s’éloigne peu à peu du littoral et serpente sur le chemin des Avocettes entre la forêt d’Olonne et les anciens marais salants devenus espace protégé. Ce tracé rejoint Les Sables d'Olonne par le port de plaisance.",
                "depart": "Saint Venant",
                "arrive": "Bethune"
              }
            }
          ]
        }
      }
    },
    {
      "id": 5,
      "attributes": {
        "NameWitness": "Christopher",
        "DateExperience": "2022-07-21",
        "createdAt": "2022-12-16T14:02:59.583Z",
        "updatedAt": "2022-12-16T15:39:31.593Z",
        "publishedAt": "2022-12-16T14:03:00.747Z",
        "NoteSecurity": 3,
        "NoteBalisage": 5,
        "NoteInterest": 4,
        "NoteService": 3,
        "Titre": "Au top !!! ",
        "Description": "Quel agréable moment passé cet été! J'ai adoré",
        "DatePublish": "2022-12-14T04:02:00.000Z",
        "Picture": {
          "data": [
            {
              "id": 13,
              "attributes": {
                "name": "champsarbre.jpg",
                "alternativeText": null,
                "caption": null,
                "width": 2048,
                "height": 1536,
                "formats": {
                  "thumbnail": {
                    "name": "thumbnail_champsarbre.jpg",
                    "hash": "thumbnail_champsarbre_d18e9b9ec2",
                    "ext": ".jpg",
                    "mime": "image/jpeg",
                    "path": null,
                    "width": 208,
                    "height": 156,
                    "size": 10.07,
                    "url": "/uploads/thumbnail_champsarbre_d18e9b9ec2.jpg"
                  },
                  "small": {
                    "name": "small_champsarbre.jpg",
                    "hash": "small_champsarbre_d18e9b9ec2",
                    "ext": ".jpg",
                    "mime": "image/jpeg",
                    "path": null,
                    "width": 500,
                    "height": 375,
                    "size": 52.63,
                    "url": "/uploads/small_champsarbre_d18e9b9ec2.jpg"
                  },
                  "medium": {
                    "name": "medium_champsarbre.jpg",
                    "hash": "medium_champsarbre_d18e9b9ec2",
                    "ext": ".jpg",
                    "mime": "image/jpeg",
                    "path": null,
                    "width": 750,
                    "height": 563,
                    "size": 111.93,
                    "url": "/uploads/medium_champsarbre_d18e9b9ec2.jpg"
                  },
                  "large": {
                    "name": "large_champsarbre.jpg",
                    "hash": "large_champsarbre_d18e9b9ec2",
                    "ext": ".jpg",
                    "mime": "image/jpeg",
                    "path": null,
                    "width": 1000,
                    "height": 750,
                    "size": 187.75,
                    "url": "/uploads/large_champsarbre_d18e9b9ec2.jpg"
                  }
                },
                "hash": "champsarbre_d18e9b9ec2",
                "ext": ".jpg",
                "mime": "image/jpeg",
                "size": 716.67,
                "url": "/uploads/champsarbre_d18e9b9ec2.jpg",
                "previewUrl": null,
                "provider": "local",
                "provider_metadata": null,
                "createdAt": "2022-12-15T13:24:08.953Z",
                "updatedAt": "2022-12-15T13:24:08.953Z"
              }
            }
          ]
        },
        "description_maps": {
          "data": [
            {
              "id": 2,
              "attributes": {
                "type": "Nature et patrimoine",
                "description": "Saint Venant est une étape incontournable de L'EuroVelo ! Station balnéaire réputée, elle est dotée d'un port actif axé sur la pêche [...]",
                "createdAt": "2022-12-15T10:20:33.187Z",
                "updatedAt": "2022-12-19T08:45:50.169Z",
                "publishedAt": "2022-12-15T10:23:53.141Z",
                "habitude_nb": 2,
                "id_infos": 3,
                "long_desc": "Saint Venant est une étape incontournable de L'EuroVelo ! Station balnéaire réputée, elle est dotée d'un port actif axé sur la pêche des poissons bleus : sardines et maquereaux. Prenez le temps de flâner sur sa grande plage avant de reprendre la route en direction de la côte vers Bethune.\n\nLa véloroute L'EuroVelo s’éloigne peu à peu du littoral et serpente sur le chemin des Avocettes entre la forêt d’Olonne et les anciens marais salants devenus espace protégé. Ce tracé rejoint Les Sables d'Olonne par le port de plaisance.",
                "depart": "Saint Venant",
                "arrive": "Bethune"
              }
            }
          ]
        }
      }
    }
  ],
  "meta": {
    "pagination": {
      "page": 1,
      "pageSize": 25,
      "pageCount": 1,
      "total": 5
    }
  }
}
